{
  "id": "party-loot",
  "title": "Party Loot",
  "description": "Track party funds and items for your campaign with a comprehensive inventory and currency management system.",
  "version": "1.0.1",
  "compatibility": {
    "minimum": "10",
    "verified": "12",
    "maximum": "12"
  },
  "authors": [
    {
      "name": "JBartholomew",
      "url": "https://github.com/jonathanbartholomew"
    }
  ],
  "esmodules": ["scripts/party-loot.js"],
  "styles": ["styles/party-loot.css"],
  "packs": [],
  "languages": [
    {
      "lang": "en",
      "name": "English",
      "path": "languages/en.json"
    }
  ],
  "socket": false,
  "url": "https://github.com/jonathanbartholomew/party-loot-vtt",
  "manifest": "https://raw.githubusercontent.com/jonathanbartholomew/party-loot-vtt/main/module.json",
  "download": "https://github.com/jonathanbartholomew/party-loot-vtt/archive/refs/tags/v1.0.1.zip",
  "readme": "https://raw.githubusercontent.com/jonathanbartholomew/party-loot-vtt/main/README.md"
}
